andystring/StringUtil.py
andystring/__init__.py
andystring-1.0.dist-info/METADATA
andystring-1.0.dist-info/WHEEL
andystring-1.0.dist-info/top_level.txt
andystring-1.0.dist-info/RECORD
