Metadata-Version: 2.1
Name: andystring
Version: 1.0
Summary: For testing deployement
Home-page: https://github.com/behappytwice/andystring
Author: Sanghyun, Kim
Author-email: behappytwice@gmail.com
License: UNKNOWN
Download-URL: https://githur.com/behappytwice/andystring/archive/1.0.tar.gz
Keywords: string util,string concatenation
Platform: UNKNOWN
Classifier: Programming Language :: Python :: 3
Classifier: Programming Language :: Python :: 3.2
Classifier: Programming Language :: Python :: 3.3
Classifier: Programming Language :: Python :: 3.4
Classifier: Programming Language :: Python :: 3.5
Classifier: Programming Language :: Python :: 3.6
Requires-Python: >=3
